brainglobe_workflows/__init__.py
brainglobe_workflows/utils.py
brainglobe_workflows/brainmapper/__init__.py
brainglobe_workflows/brainmapper/analyse.py
brainglobe_workflows/brainmapper/main.py
brainglobe_workflows/brainmapper/parser.py
brainglobe_workflows/brainmapper/prep.py
brainglobe_workflows/cellfinder/__init__.py
brainglobe_workflows/cellfinder/cellfinder.py
brainglobe_workflows/configs/cellfinder.json
brainglobe_workflows-1.4.1.dist-info/LICENSE
brainglobe_workflows-1.4.1.dist-info/METADATA
brainglobe_workflows-1.4.1.dist-info/WHEEL
brainglobe_workflows-1.4.1.dist-info/entry_points.txt
brainglobe_workflows-1.4.1.dist-info/top_level.txt
brainglobe_workflows-1.4.1.dist-info/RECORD
