Metadata-Version: 2.2
Name: brainglobe-workflows
Version: 1.4.1
Summary: A collection of end-to-end data analysis workflows executed using BrainGlobe tools.
Author: Christian Niedworok, Charly Rousseau
Author-email: Adam Tyson <code@adamltyson.com>, BrainGlobe developers <code@adamltyson.com>
License: BSD 3-Clause License
Project-URL: Bug Tracker, https://github.com/brainglobe/brainglobe-workflows/issues
Project-URL: Documentation, https://brainglobe.info/documentation/brainglobe-workflows
Project-URL: Homepage, https://brainglobe.info
Project-URL: Source Code, https://github.com/brainglobe/brainglobe-workflows
Classifier: Development Status :: 3 - Alpha
Classifier: Intended Audience :: Developers
Classifier: Intended Audience :: Science/Research
Classifier: License :: OSI Approved :: BSD License
Classifier: Operating System :: OS Independent
Classifier: Programming Language :: Python :: 3.11
Classifier: Programming Language :: Python :: 3.12
Classifier: Programming Language :: Python :: 3.13
Classifier: Programming Language :: Python
Classifier: Topic :: Scientific/Engineering :: Image Recognition
Requires-Python: >=3.11
License-File: LICENSE
Requires-Dist: brainglobe>=1.3.0
Requires-Dist: brainglobe-utils>=0.7.0
Requires-Dist: configobj
Requires-Dist: fancylog>=0.4.2
Requires-Dist: multiprocessing-logging>=0.3.4
Requires-Dist: natsort
Requires-Dist: numpy
Requires-Dist: pandas
Requires-Dist: packaging
Requires-Dist: pooch
Requires-Dist: scikit-image
Requires-Dist: tifffile
Requires-Dist: tqdm
Provides-Extra: dev
Requires-Dist: black; extra == "dev"
Requires-Dist: pytest-cov; extra == "dev"
Requires-Dist: pytest; extra == "dev"
Requires-Dist: gitpython; extra == "dev"
Requires-Dist: coverage>=5.0.3; extra == "dev"
Requires-Dist: pre-commit; extra == "dev"
Requires-Dist: setuptools_scm; extra == "dev"
Requires-Dist: asv; extra == "dev"
Provides-Extra: napari
Requires-Dist: napari[pyqt5]; extra == "napari"
Requires-Dist: brainglobe-napari-io; extra == "napari"
Requires-Dist: cellfinder[napari]>=1.0.0; extra == "napari"
